{
    "aliases": [],
    "executables": [
        {
            "is_launcher": false,
            "name": "rain world/rainworld.exe",
            "os": "win32"
        }
    ],
    "hook": true,
    "id": "1124352106107777134",
    "name": "Rain World",
    "overlay": false,
    "overlay_compatibility_hook": false,
    "overlay_methods": null,
    "overlay_warn": false,
    "themes": [
        "Action",
        "Science fiction",
        "Horror",
        "Survival",
        "Open world"
    ]
}