{
    "aliases": [],
    "executables": [
        {
            "is_launcher": false,
            "name": "sheepy a short adventure/sheepyashortadventure.exe",
            "os": "win32"
        }
    ],
    "hook": true,
    "id": "1206132537764880425",
    "name": "Sheepy: A Short Adventure",
    "overlay": false,
    "overlay_compatibility_hook": false,
    "overlay_methods": null,
    "overlay_warn": false,
    "themes": [
        "Fantasy",
        "Horror",
        "Survival",
        "Mystery"
    ]
}