{
    "aliases": [
        "Assassin's Creed: Revelations"
    ],
    "executables": [
        {
            "is_launcher": false,
            "name": "acrsp.exe",
            "os": "win32"
        }
    ],
    "hook": true,
    "id": "425436928041680931",
    "name": "Assassin's Creed Revelations",
    "overlay": false,
    "overlay_compatibility_hook": false,
    "overlay_methods": null,
    "overlay_warn": false,
    "themes": [
        "Action",
        "Fantasy",
        "Historical",
        "Stealth",
        "Sandbox",
        "Open world"
    ]
}